JianZhiOfferTijieItcharge/README.md
JianZhiOfferTijieItcharge/__init__.py
JianZhiOfferTijieItcharge/__main__.py
JianZhiOfferTijieItcharge/file.epub
JianZhiOfferTijieItcharge/index.html
JianZhiOfferTijieItcharge/css/__init__.py
JianZhiOfferTijieItcharge/css/annotations.css
JianZhiOfferTijieItcharge/css/main.css
JianZhiOfferTijieItcharge/css/normalize.css
JianZhiOfferTijieItcharge/css/popup.css
JianZhiOfferTijieItcharge/font/__init__.py
JianZhiOfferTijieItcharge/font/fontello.eot
JianZhiOfferTijieItcharge/font/fontello.svg
JianZhiOfferTijieItcharge/font/fontello.ttf
JianZhiOfferTijieItcharge/font/fontello.woff
JianZhiOfferTijieItcharge/img/__init__.py
JianZhiOfferTijieItcharge/img/annotator-glyph-sprite.png
JianZhiOfferTijieItcharge/img/annotator-icon-sprite.png
JianZhiOfferTijieItcharge/img/apple-touch-icon.png
JianZhiOfferTijieItcharge/img/cancelfullscreen.png
JianZhiOfferTijieItcharge/img/close.png
JianZhiOfferTijieItcharge/img/fullscreen.png
JianZhiOfferTijieItcharge/img/loader.gif
JianZhiOfferTijieItcharge/img/menu-icon.png
JianZhiOfferTijieItcharge/img/save.png
JianZhiOfferTijieItcharge/img/saved.png
JianZhiOfferTijieItcharge/img/settings-s.png
JianZhiOfferTijieItcharge/img/settings.png
JianZhiOfferTijieItcharge/img/star.png
JianZhiOfferTijieItcharge/js/__init__.py
JianZhiOfferTijieItcharge/js/epub.js
JianZhiOfferTijieItcharge/js/epub.min.js
JianZhiOfferTijieItcharge/js/epub.min.map
JianZhiOfferTijieItcharge/js/hooks.min.js
JianZhiOfferTijieItcharge/js/hooks.min.map
JianZhiOfferTijieItcharge/js/reader.js
JianZhiOfferTijieItcharge/js/reader.js.map
JianZhiOfferTijieItcharge/js/reader.min.js
JianZhiOfferTijieItcharge/js/reader.min.map
JianZhiOfferTijieItcharge/js/hooks/__init__.py
JianZhiOfferTijieItcharge/js/hooks/extensions/__init__.py
JianZhiOfferTijieItcharge/js/hooks/extensions/highlight.js
JianZhiOfferTijieItcharge/js/libs/__init__.py
JianZhiOfferTijieItcharge/js/libs/jquery.min.js
JianZhiOfferTijieItcharge/js/libs/localforage.min.js
jian_zhi_offer_tijie_itcharge-2024.3.5.0.dist-info/METADATA
jian_zhi_offer_tijie_itcharge-2024.3.5.0.dist-info/WHEEL
jian_zhi_offer_tijie_itcharge-2024.3.5.0.dist-info/entry_points.txt
jian_zhi_offer_tijie_itcharge-2024.3.5.0.dist-info/top_level.txt
jian_zhi_offer_tijie_itcharge-2024.3.5.0.dist-info/RECORD
